llfpga/__init__.py
llfpga/register.py
llfpga/rpc.py
llfpga-0.0.1.dist-info/METADATA
llfpga-0.0.1.dist-info/WHEEL
llfpga-0.0.1.dist-info/top_level.txt
llfpga-0.0.1.dist-info/RECORD
